graph_retriever/__init__.py
graph_retriever/content.py
graph_retriever/py.typed
graph_retriever/traversal.py
graph_retriever/types.py
graph_retriever/adapters/__init__.py
graph_retriever/adapters/base.py
graph_retriever/adapters/in_memory.py
graph_retriever/edges/__init__.py
graph_retriever/edges/_base.py
graph_retriever/edges/metadata.py
graph_retriever/strategies/__init__.py
graph_retriever/strategies/base.py
graph_retriever/strategies/eager.py
graph_retriever/strategies/mmr.py
graph_retriever/strategies/scored.py
graph_retriever/testing/__init__.py
graph_retriever/testing/adapter_tests.py
graph_retriever/testing/embeddings.py
graph_retriever/utils/__init__.py
graph_retriever/utils/batched.py
graph_retriever/utils/math.py
graph_retriever/utils/merge.py
graph_retriever/utils/run_in_executor.py
graph_retriever/utils/top_k.py
graph_retriever-0.8.0.dist-info/METADATA
graph_retriever-0.8.0.dist-info/WHEEL
graph_retriever-0.8.0.dist-info/licenses/LICENSE
graph_retriever-0.8.0.dist-info/RECORD
